<?xml version="1.0" ?>
 <trains>
  <train>
   <train_number>758</train_number>
   <depart_st>Vernon</depart_st>
   <arriv_st>York</arriv_st>
   <data_of_departure>8/11/2002 14:49:36</data_of_departure>
   <data_of_arrival>15/5/2009 24:31:31</data_of_arrival>
  </train>
  <train>
   <train_number>144</train_number>
   <depart_st>Plattsburgh</depart_st>
   <arriv_st>Woodstock</arriv_st>
   <data_of_departure>15/3/2002 24:14:36</data_of_departure>
   <data_of_arrival>31/3/2007 18:4:28</data_of_arrival>
  </train>
  <train>
   <train_number>851</train_number>
   <depart_st>Herkimer</depart_st>
   <arriv_st>Point</arriv_st>
   <data_of_departure>12/3/2001 9:35:52</data_of_departure>
   <data_of_arrival>4/11/2009 13:15:5</data_of_arrival>
  </train>
  <train>
   <train_number>337</train_number>
   <depart_st>Mamaroneck</depart_st>
   <arriv_st>Auburn</arriv_st>
   <data_of_departure>24/6/2000 8:33:46</data_of_departure>
   <data_of_arrival>1/5/2006 6:16:48</data_of_arrival>
  </train>
  <train>
   <train_number>729</train_number>
   <depart_st>Stony</depart_st>
   <arriv_st>Mineola</arriv_st>
   <data_of_departure>20/5/2002 1:14:50</data_of_departure>
   <data_of_arrival>9/10/2009 4:56:35</data_of_arrival>
  </train>
  <train>
   <train_number>532</train_number>
   <depart_st>Huntington</depart_st>
   <arriv_st>Glen</arriv_st>
   <data_of_departure>2/4/2000 22:3:48</data_of_departure>
   <data_of_arrival>6/10/2005 17:17:22</data_of_arrival>
  </train>
  <train>
   <train_number>843</train_number>
   <depart_st>Middletown</depart_st>
   <arriv_st>Palmyra</arriv_st>
   <data_of_departure>1/4/2005 4:41:48</data_of_departure>
   <data_of_arrival>10/11/2009 8:13:50</data_of_arrival>
  </train>
  <train>
   <train_number>872</train_number>
   <depart_st>Oswego</depart_st>
   <arriv_st>Aurora</arriv_st>
   <data_of_departure>13/3/2000 6:43:33</data_of_departure>
   <data_of_arrival>20/4/2005 22:6:8</data_of_arrival>
  </train>
  <train>
   <train_number>862</train_number>
   <depart_st>Utica</depart_st>
   <arriv_st>Ogdensburg</arriv_st>
   <data_of_departure>28/3/2000 23:27:58</data_of_departure>
   <data_of_arrival>24/4/2008 3:34:52</data_of_arrival>
  </train>
  <train>
   <train_number>676</train_number>
   <depart_st>Placid</depart_st>
   <arriv_st>Hempstead</arriv_st>
   <data_of_departure>15/8/2000 9:18:56</data_of_departure>
   <data_of_arrival>8/5/2007 10:11:28</data_of_arrival>
  </train>
  <train>
   <train_number>918</train_number>
   <depart_st>Oyster</depart_st>
   <arriv_st>Clinton</arriv_st>
   <data_of_departure>30/3/2003 20:41:15</data_of_departure>
   <data_of_arrival>13/2/2005 1:51:4</data_of_arrival>
  </train>
  <train>
   <train_number>529</train_number>
   <depart_st>Saranac</depart_st>
   <arriv_st>Garden</arriv_st>
   <data_of_departure>21/1/2000 13:11:45</data_of_departure>
   <data_of_arrival>14/1/2009 5:7:4</data_of_arrival>
  </train>
  <train>
   <train_number>750</train_number>
   <depart_st>Hyde</depart_st>
   <arriv_st>Point</arriv_st>
   <data_of_departure>17/7/2001 13:13:17</data_of_departure>
   <data_of_arrival>13/12/2010 3:18:36</data_of_arrival>
  </train>
  <train>
   <train_number>975</train_number>
   <depart_st>Oswego</depart_st>
   <arriv_st>Mamaroneck</arriv_st>
   <data_of_departure>10/6/2001 10:36:36</data_of_departure>
   <data_of_arrival>30/1/2007 16:57:40</data_of_arrival>
  </train>
  <train>
   <train_number>606</train_number>
   <depart_st>Cooperstown</depart_st>
   <arriv_st>Rotterdam</arriv_st>
   <data_of_departure>21/5/2000 15:25:30</data_of_departure>
   <data_of_arrival>20/8/2006 3:19:19</data_of_arrival>
  </train>
  <train>
   <train_number>548</train_number>
   <depart_st>Saranac</depart_st>
   <arriv_st>Massena</arriv_st>
   <data_of_departure>16/8/2005 23:24:25</data_of_departure>
   <data_of_arrival>14/8/2007 3:47:23</data_of_arrival>
  </train>
  <train>
   <train_number>992</train_number>
   <depart_st>New</depart_st>
   <arriv_st>Binghamton</arriv_st>
   <data_of_departure>4/3/2002 4:22:26</data_of_departure>
   <data_of_arrival>6/3/2008 16:60:40</data_of_arrival>
  </train>
  <train>
   <train_number>97</train_number>
   <depart_st>City</depart_st>
   <arriv_st>Falls</arriv_st>
   <data_of_departure>12/6/2001 9:59:22</data_of_departure>
   <data_of_arrival>20/4/2008 14:48:36</data_of_arrival>
  </train>
  <train>
   <train_number>706</train_number>
   <depart_st>New</depart_st>
   <arriv_st>Rye</arriv_st>
   <data_of_departure>31/9/2000 14:45:60</data_of_departure>
   <data_of_arrival>13/10/2010 15:34:16</data_of_arrival>
  </train>
  <train>
   <train_number>259</train_number>
   <depart_st>Hampton</depart_st>
   <arriv_st>Seneca</arriv_st>
   <data_of_departure>26/3/2002 18:34:28</data_of_departure>
   <data_of_arrival>2/8/2010 9:52:5</data_of_arrival>
  </train>
  <train>
   <train_number>128</train_number>
   <depart_st>Placid</depart_st>
   <arriv_st>Bronx</arriv_st>
   <data_of_departure>19/9/2000 11:14:41</data_of_departure>
   <data_of_arrival>1/2/2009 1:54:51</data_of_arrival>
  </train>
  <train>
   <train_number>412</train_number>
   <depart_st>Cohoes</depart_st>
   <arriv_st>Rochester</arriv_st>
   <data_of_departure>14/9/2003 3:58:60</data_of_departure>
   <data_of_arrival>3/12/2010 17:33:53</data_of_arrival>
  </train>
  <train>
   <train_number>619</train_number>
   <depart_st>Clinton</depart_st>
   <arriv_st>Clinton</arriv_st>
   <data_of_departure>22/2/2005 10:17:7</data_of_departure>
   <data_of_arrival>17/1/2009 5:33:56</data_of_arrival>
  </train>
  <train>
   <train_number>30</train_number>
   <depart_st>Port</depart_st>
   <arriv_st>Coney</arriv_st>
   <data_of_departure>19/5/2002 19:30:7</data_of_departure>
   <data_of_arrival>18/5/2007 4:35:42</data_of_arrival>
  </train>
  <train>
   <train_number>274</train_number>
   <depart_st>Bay</depart_st>
   <arriv_st>Auburn</arriv_st>
   <data_of_departure>25/9/2004 14:26:21</data_of_departure>
   <data_of_arrival>16/7/2007 7:41:47</data_of_arrival>
  </train>
  <train>
   <train_number>419</train_number>
   <depart_st>Tarrytown</depart_st>
   <arriv_st>Neck</arriv_st>
   <data_of_departure>20/11/2003 3:49:26</data_of_departure>
   <data_of_arrival>4/2/2009 19:26:50</data_of_arrival>
  </train>
  <train>
   <train_number>13</train_number>
   <depart_st>Troy</depart_st>
   <arriv_st>Flushing</arriv_st>
   <data_of_departure>23/9/2004 12:53:4</data_of_departure>
   <data_of_arrival>2/10/2005 4:55:27</data_of_arrival>
  </train>
  <train>
   <train_number>13</train_number>
   <depart_st>Batavia</depart_st>
   <arriv_st>Cortland</arriv_st>
   <data_of_departure>15/1/2002 4:49:42</data_of_departure>
   <data_of_arrival>14/5/2006 5:37:58</data_of_arrival>
  </train>
  <train>
   <train_number>159</train_number>
   <depart_st>Troy</depart_st>
   <arriv_st>Island</arriv_st>
   <data_of_departure>30/12/2001 16:40:17</data_of_departure>
   <data_of_arrival>23/8/2010 13:40:27</data_of_arrival>
  </train>
  <train>
   <train_number>779</train_number>
   <depart_st>New</depart_st>
   <arriv_st>Hills</arriv_st>
   <data_of_departure>18/4/2004 3:46:57</data_of_departure>
   <data_of_arrival>11/8/2008 24:18:14</data_of_arrival>
  </train>
  <train>
   <train_number>292</train_number>
   <depart_st>Hampton</depart_st>
   <arriv_st>Rotterdam</arriv_st>
   <data_of_departure>12/4/2004 3:31:10</data_of_departure>
   <data_of_arrival>24/5/2008 6:50:12</data_of_arrival>
  </train>
  <train>
   <train_number>383</train_number>
   <depart_st>Watkins</depart_st>
   <arriv_st>Eastchester</arriv_st>
   <data_of_departure>3/2/2005 23:22:18</data_of_departure>
   <data_of_arrival>23/7/2009 1:5:55</data_of_arrival>
  </train>
  <train>
   <train_number>278</train_number>
   <depart_st>Coney</depart_st>
   <arriv_st>Newburgh</arriv_st>
   <data_of_departure>15/6/2005 4:27:15</data_of_departure>
   <data_of_arrival>19/10/2006 11:58:37</data_of_arrival>
  </train>
  <train>
   <train_number>683</train_number>
   <depart_st>Scarsdale</depart_st>
   <arriv_st>Port</arriv_st>
   <data_of_departure>8/1/2003 23:15:16</data_of_departure>
   <data_of_arrival>29/10/2005 17:20:50</data_of_arrival>
  </train>
  <train>
   <train_number>951</train_number>
   <depart_st>Bedford</depart_st>
   <arriv_st>Manhattan</arriv_st>
   <data_of_departure>9/1/2000 2:32:2</data_of_departure>
   <data_of_arrival>11/2/2005 5:54:57</data_of_arrival>
  </train>
  <train>
   <train_number>526</train_number>
   <depart_st>Nyack</depart_st>
   <arriv_st>Ossining</arriv_st>
   <data_of_departure>22/7/2005 11:46:37</data_of_departure>
   <data_of_arrival>12/6/2007 8:25:20</data_of_arrival>
  </train>
  <train>
   <train_number>466</train_number>
   <depart_st>Mamaroneck</depart_st>
   <arriv_st>Southampton</arriv_st>
   <data_of_departure>24/4/2002 15:27:30</data_of_departure>
   <data_of_arrival>13/6/2009 8:37:44</data_of_arrival>
  </train>
  <train>
   <train_number>536</train_number>
   <depart_st>Dunkirk</depart_st>
   <arriv_st>Fredonia</arriv_st>
   <data_of_departure>17/7/2001 11:39:44</data_of_departure>
   <data_of_arrival>3/8/2007 21:18:46</data_of_arrival>
  </train>
  <train>
   <train_number>457</train_number>
   <depart_st>Palmyra</depart_st>
   <arriv_st>Watervliet</arriv_st>
   <data_of_departure>7/4/2003 8:53:15</data_of_departure>
   <data_of_arrival>10/1/2005 22:14:60</data_of_arrival>
  </train>
  <train>
   <train_number>681</train_number>
   <depart_st>Placid</depart_st>
   <arriv_st>Cheektowaga</arriv_st>
   <data_of_departure>18/9/2003 12:52:53</data_of_departure>
   <data_of_arrival>11/6/2008 23:45:36</data_of_arrival>
  </train>
  <train>
   <train_number>635</train_number>
   <depart_st>Rye</depart_st>
   <arriv_st>Levittown</arriv_st>
   <data_of_departure>4/8/2005 22:27:19</data_of_departure>
   <data_of_arrival>11/8/2007 12:52:10</data_of_arrival>
  </train>
  <train>
   <train_number>957</train_number>
   <depart_st>Albany</depart_st>
   <arriv_st>Rye</arriv_st>
   <data_of_departure>10/11/2002 8:42:40</data_of_departure>
   <data_of_arrival>4/2/2008 11:52:2</data_of_arrival>
  </train>
  <train>
   <train_number>149</train_number>
   <depart_st>Newburgh</depart_st>
   <arriv_st>Springs</arriv_st>
   <data_of_departure>5/12/2001 13:34:11</data_of_departure>
   <data_of_arrival>22/1/2006 20:13:27</data_of_arrival>
  </train>
  <train>
   <train_number>379</train_number>
   <depart_st>Fredonia</depart_st>
   <arriv_st>Kingston</arriv_st>
   <data_of_departure>15/5/2001 1:35:10</data_of_departure>
   <data_of_arrival>10/6/2006 22:51:54</data_of_arrival>
  </train>
  <train>
   <train_number>58</train_number>
   <depart_st>Hammondsport</depart_st>
   <arriv_st>Great</arriv_st>
   <data_of_departure>2/8/2005 20:36:43</data_of_departure>
   <data_of_arrival>27/8/2008 8:4:10</data_of_arrival>
  </train>
  <train>
   <train_number>223</train_number>
   <depart_st>Ossining</depart_st>
   <arriv_st>Cohoes</arriv_st>
   <data_of_departure>5/4/2004 4:32:48</data_of_departure>
   <data_of_arrival>24/1/2010 12:7:55</data_of_arrival>
  </train>
  <train>
   <train_number>272</train_number>
   <depart_st>Manhattan</depart_st>
   <arriv_st>Albany</arriv_st>
   <data_of_departure>25/7/2003 2:49:18</data_of_departure>
   <data_of_arrival>7/5/2010 20:16:12</data_of_arrival>
  </train>
  <train>
   <train_number>768</train_number>
   <depart_st>Newburgh</depart_st>
   <arriv_st>Kingston</arriv_st>
   <data_of_departure>28/7/2004 17:24:5</data_of_departure>
   <data_of_arrival>14/7/2010 24:51:20</data_of_arrival>
  </train>
  <train>
   <train_number>978</train_number>
   <depart_st>Potsdam</depart_st>
   <arriv_st>Olean</arriv_st>
   <data_of_departure>17/6/2002 3:35:33</data_of_departure>
   <data_of_arrival>12/1/2006 11:25:15</data_of_arrival>
  </train>
  <train>
   <train_number>491</train_number>
   <depart_st>Gloversville</depart_st>
   <arriv_st>East</arriv_st>
   <data_of_departure>18/11/2002 5:32:19</data_of_departure>
   <data_of_arrival>5/11/2010 14:9:32</data_of_arrival>
  </train>
  <train>
   <train_number>561</train_number>
   <depart_st>Utica</depart_st>
   <arriv_st>West</arriv_st>
   <data_of_departure>14/5/2004 14:34:45</data_of_departure>
   <data_of_arrival>13/8/2006 17:4:55</data_of_arrival>
  </train>
  <train>
   <train_number>5</train_number>
   <depart_st>Fredonia</depart_st>
   <arriv_st>Elmira</arriv_st>
   <data_of_departure>8/10/2005 19:13:10</data_of_departure>
   <data_of_arrival>28/9/2010 1:16:33</data_of_arrival>
  </train>
  <train>
   <train_number>120</train_number>
   <depart_st>Harbor</depart_st>
   <arriv_st>Island</arriv_st>
   <data_of_departure>17/8/2005 12:44:29</data_of_departure>
   <data_of_arrival>17/2/2010 6:33:2</data_of_arrival>
  </train>
  <train>
   <train_number>308</train_number>
   <depart_st>Falls</depart_st>
   <arriv_st>Hempstead</arriv_st>
   <data_of_departure>17/7/2004 23:12:34</data_of_departure>
   <data_of_arrival>7/6/2007 19:52:13</data_of_arrival>
  </train>
  <train>
   <train_number>158</train_number>
   <depart_st>Lake</depart_st>
   <arriv_st>Levittown</arriv_st>
   <data_of_departure>27/9/2001 4:36:42</data_of_departure>
   <data_of_arrival>13/2/2006 20:46:31</data_of_arrival>
  </train>
  <train>
   <train_number>641</train_number>
   <depart_st>Schenectady</depart_st>
   <arriv_st>East</arriv_st>
   <data_of_departure>7/1/2001 2:49:43</data_of_departure>
   <data_of_arrival>5/12/2008 16:56:30</data_of_arrival>
  </train>
  <train>
   <train_number>915</train_number>
   <depart_st>New</depart_st>
   <arriv_st>Rome</arriv_st>
   <data_of_departure>7/1/2002 15:2:15</data_of_departure>
   <data_of_arrival>4/7/2007 22:24:59</data_of_arrival>
  </train>
  <train>
   <train_number>737</train_number>
   <depart_st>Potsdam</depart_st>
   <arriv_st>Hampton</arriv_st>
   <data_of_departure>20/2/2001 3:9:3</data_of_departure>
   <data_of_arrival>8/4/2005 11:22:23</data_of_arrival>
  </train>
  <train>
   <train_number>709</train_number>
   <depart_st>New</depart_st>
   <arriv_st>Johnstown</arriv_st>
   <data_of_departure>31/1/2004 18:52:48</data_of_departure>
   <data_of_arrival>18/8/2007 13:31:41</data_of_arrival>
  </train>
  <train>
   <train_number>717</train_number>
   <depart_st>Bedford</depart_st>
   <arriv_st>Oneida</arriv_st>
   <data_of_departure>5/9/2005 21:20:43</data_of_departure>
   <data_of_arrival>9/12/2010 15:7:16</data_of_arrival>
  </train>
  <train>
   <train_number>465</train_number>
   <depart_st>Saratoga</depart_st>
   <arriv_st>Falls</arriv_st>
   <data_of_departure>11/1/2001 20:24:12</data_of_departure>
   <data_of_arrival>18/2/2006 9:50:7</data_of_arrival>
  </train>
  <train>
   <train_number>666</train_number>
   <depart_st>Rye</depart_st>
   <arriv_st>Levittown</arriv_st>
   <data_of_departure>24/10/2005 23:47:12</data_of_departure>
   <data_of_arrival>1/6/2005 7:5:60</data_of_arrival>
  </train>
  <train>
   <train_number>480</train_number>
   <depart_st>Rotterdam</depart_st>
   <arriv_st>Lockport</arriv_st>
   <data_of_departure>15/9/2003 4:26:40</data_of_departure>
   <data_of_arrival>22/3/2006 21:59:37</data_of_arrival>
  </train>
  <train>
   <train_number>224</train_number>
   <depart_st>Buffalo</depart_st>
   <arriv_st>Tonawanda</arriv_st>
   <data_of_departure>13/7/2005 17:19:11</data_of_departure>
   <data_of_arrival>17/4/2007 3:11:10</data_of_arrival>
  </train>
  <train>
   <train_number>102</train_number>
   <depart_st>Brook</depart_st>
   <arriv_st>Bedford</arriv_st>
   <data_of_departure>15/5/2005 14:40:42</data_of_departure>
   <data_of_arrival>21/5/2009 1:27:24</data_of_arrival>
  </train>
  <train>
   <train_number>114</train_number>
   <depart_st>Staten</depart_st>
   <arriv_st>Rome</arriv_st>
   <data_of_departure>11/1/2000 15:27:12</data_of_departure>
   <data_of_arrival>26/6/2005 17:43:37</data_of_arrival>
  </train>
  <train>
   <train_number>915</train_number>
   <depart_st>Brooklyn</depart_st>
   <arriv_st>Southampton</arriv_st>
   <data_of_departure>1/3/2003 9:12:37</data_of_departure>
   <data_of_arrival>22/11/2007 11:17:55</data_of_arrival>
  </train>
  <train>
   <train_number>670</train_number>
   <depart_st>East</depart_st>
   <arriv_st>Seneca</arriv_st>
   <data_of_departure>25/1/2001 19:19:35</data_of_departure>
   <data_of_arrival>1/8/2007 15:41:50</data_of_arrival>
  </train>
  <train>
   <train_number>137</train_number>
   <depart_st>Plattsburgh</depart_st>
   <arriv_st>Oyster</arriv_st>
   <data_of_departure>4/9/2002 18:22:57</data_of_departure>
   <data_of_arrival>17/1/2005 15:21:41</data_of_arrival>
  </train>
  <train>
   <train_number>698</train_number>
   <depart_st>Lockport</depart_st>
   <arriv_st>Gloversville</arriv_st>
   <data_of_departure>20/8/2002 6:17:24</data_of_departure>
   <data_of_arrival>27/5/2008 18:3:16</data_of_arrival>
  </train>
  <train>
   <train_number>880</train_number>
   <depart_st>Falls</depart_st>
   <arriv_st>Park</arriv_st>
   <data_of_departure>22/7/2002 2:3:34</data_of_departure>
   <data_of_arrival>7/1/2005 21:3:13</data_of_arrival>
  </train>
  <train>
   <train_number>594</train_number>
   <depart_st>Fredonia</depart_st>
   <arriv_st>Syracuse</arriv_st>
   <data_of_departure>16/3/2000 6:41:22</data_of_departure>
   <data_of_arrival>27/7/2006 18:57:39</data_of_arrival>
  </train>
  <train>
   <train_number>797</train_number>
   <depart_st>Manhattan</depart_st>
   <arriv_st>Hempstead</arriv_st>
   <data_of_departure>28/7/2002 12:15:58</data_of_departure>
   <data_of_arrival>1/3/2005 24:2:25</data_of_arrival>
  </train>
  <train>
   <train_number>246</train_number>
   <depart_st>Garden</depart_st>
   <arriv_st>Scarsdale</arriv_st>
   <data_of_departure>14/12/2000 15:5:8</data_of_departure>
   <data_of_arrival>1/7/2006 21:46:3</data_of_arrival>
  </train>
  <train>
   <train_number>368</train_number>
   <depart_st>City</depart_st>
   <arriv_st>Brook</arriv_st>
   <data_of_departure>3/3/2000 4:58:25</data_of_departure>
   <data_of_arrival>5/12/2007 8:37:15</data_of_arrival>
  </train>
  <train>
   <train_number>374</train_number>
   <depart_st>Lake</depart_st>
   <arriv_st>Tonawanda</arriv_st>
   <data_of_departure>12/10/2003 23:18:48</data_of_departure>
   <data_of_arrival>11/1/2010 24:23:12</data_of_arrival>
  </train>
  <train>
   <train_number>904</train_number>
   <depart_st>Syracuse</depart_st>
   <arriv_st>Placid</arriv_st>
   <data_of_departure>4/11/2004 5:18:28</data_of_departure>
   <data_of_arrival>29/9/2008 6:34:29</data_of_arrival>
  </train>
  <train>
   <train_number>730</train_number>
   <depart_st>Cheektowaga</depart_st>
   <arriv_st>Dunkirk</arriv_st>
   <data_of_departure>9/4/2000 1:44:48</data_of_departure>
   <data_of_arrival>17/10/2007 16:45:11</data_of_arrival>
  </train>
  <train>
   <train_number>991</train_number>
   <depart_st>Potsdam</depart_st>
   <arriv_st>Point</arriv_st>
   <data_of_departure>14/12/2000 12:35:12</data_of_departure>
   <data_of_arrival>2/2/2005 13:41:1</data_of_arrival>
  </train>
  <train>
   <train_number>420</train_number>
   <depart_st>Staten</depart_st>
   <arriv_st>Johnstown</arriv_st>
   <data_of_departure>3/3/2000 1:58:15</data_of_departure>
   <data_of_arrival>18/1/2009 2:50:19</data_of_arrival>
  </train>
  <train>
   <train_number>359</train_number>
   <depart_st>Rochelle</depart_st>
   <arriv_st>Dunkirk</arriv_st>
   <data_of_departure>15/6/2004 24:2:44</data_of_departure>
   <data_of_arrival>12/2/2005 7:29:18</data_of_arrival>
  </train>
  <train>
   <train_number>5</train_number>
   <depart_st>Port</depart_st>
   <arriv_st>Peekskill</arriv_st>
   <data_of_departure>27/6/2002 22:34:27</data_of_departure>
   <data_of_arrival>18/6/2005 4:4:25</data_of_arrival>
  </train>
  <train>
   <train_number>474</train_number>
   <depart_st>Lackawanna</depart_st>
   <arriv_st>Port</arriv_st>
   <data_of_departure>25/1/2001 20:4:53</data_of_departure>
   <data_of_arrival>27/6/2009 21:44:43</data_of_arrival>
  </train>
  <train>
   <train_number>967</train_number>
   <depart_st>Watkins</depart_st>
   <arriv_st>Amsterdam</arriv_st>
   <data_of_departure>16/12/2003 7:24:26</data_of_departure>
   <data_of_arrival>29/9/2005 11:26:39</data_of_arrival>
  </train>
  <train>
   <train_number>23</train_number>
   <depart_st>Schenectady</depart_st>
   <arriv_st>Cohoes</arriv_st>
   <data_of_departure>8/7/2004 22:31:24</data_of_departure>
   <data_of_arrival>30/4/2006 9:19:23</data_of_arrival>
  </train>
  <train>
   <train_number>203</train_number>
   <depart_st>Island</depart_st>
   <arriv_st>Glens</arriv_st>
   <data_of_departure>5/6/2000 6:44:26</data_of_departure>
   <data_of_arrival>5/4/2006 18:4:4</data_of_arrival>
  </train>
  <train>
   <train_number>520</train_number>
   <depart_st>Brooklyn</depart_st>
   <arriv_st>Mineola</arriv_st>
   <data_of_departure>4/3/2002 23:26:27</data_of_departure>
   <data_of_arrival>22/8/2006 21:53:59</data_of_arrival>
  </train>
  <train>
   <train_number>738</train_number>
   <depart_st>Queens</depart_st>
   <arriv_st>Peekskill</arriv_st>
   <data_of_departure>16/12/2004 8:39:56</data_of_departure>
   <data_of_arrival>20/5/2006 2:24:17</data_of_arrival>
  </train>
  <train>
   <train_number>446</train_number>
   <depart_st>Scarsdale</depart_st>
   <arriv_st>Clinton</arriv_st>
   <data_of_departure>17/12/2005 24:28:17</data_of_departure>
   <data_of_arrival>21/5/2010 12:49:8</data_of_arrival>
  </train>
  <train>
   <train_number>784</train_number>
   <depart_st>City</depart_st>
   <arriv_st>Hyde</arriv_st>
   <data_of_departure>8/1/2000 5:31:11</data_of_departure>
   <data_of_arrival>3/9/2009 24:27:15</data_of_arrival>
  </train>
  <train>
   <train_number>813</train_number>
   <depart_st>Springs</depart_st>
   <arriv_st>Harlem</arriv_st>
   <data_of_departure>6/9/2002 15:36:8</data_of_departure>
   <data_of_arrival>4/8/2008 14:39:6</data_of_arrival>
  </train>
  <train>
   <train_number>436</train_number>
   <depart_st>Park</depart_st>
   <arriv_st>Paltz</arriv_st>
   <data_of_departure>16/2/2005 13:14:31</data_of_departure>
   <data_of_arrival>16/9/2006 18:39:22</data_of_arrival>
  </train>
  <train>
   <train_number>314</train_number>
   <depart_st>Rochester</depart_st>
   <arriv_st>Eastchester</arriv_st>
   <data_of_departure>23/12/2003 19:24:51</data_of_departure>
   <data_of_arrival>16/8/2007 2:54:57</data_of_arrival>
  </train>
  <train>
   <train_number>33</train_number>
   <depart_st>Garden</depart_st>
   <arriv_st>Poughkeepsie</arriv_st>
   <data_of_departure>25/11/2000 22:58:33</data_of_departure>
   <data_of_arrival>4/3/2010 5:21:38</data_of_arrival>
  </train>
  <train>
   <train_number>183</train_number>
   <depart_st>Windsor</depart_st>
   <arriv_st>Johnstown</arriv_st>
   <data_of_departure>16/4/2002 6:53:54</data_of_departure>
   <data_of_arrival>29/7/2007 23:32:11</data_of_arrival>
  </train>
  <train>
   <train_number>292</train_number>
   <depart_st>Sag</depart_st>
   <arriv_st>Seneca</arriv_st>
   <data_of_departure>17/8/2003 6:33:24</data_of_departure>
   <data_of_arrival>5/6/2006 10:16:4</data_of_arrival>
  </train>
  <train>
   <train_number>908</train_number>
   <depart_st>Fredonia</depart_st>
   <arriv_st>Huntington</arriv_st>
   <data_of_departure>17/1/2001 19:45:47</data_of_departure>
   <data_of_arrival>11/9/2010 4:32:31</data_of_arrival>
  </train>
  <train>
   <train_number>554</train_number>
   <depart_st>Ticonderoga</depart_st>
   <arriv_st>East</arriv_st>
   <data_of_departure>11/2/2005 22:2:5</data_of_departure>
   <data_of_arrival>26/9/2005 19:3:55</data_of_arrival>
  </train>
  <train>
   <train_number>17</train_number>
   <depart_st>Babylon</depart_st>
   <arriv_st>Plains</arriv_st>
   <data_of_departure>23/4/2001 23:3:50</data_of_departure>
   <data_of_arrival>31/1/2007 22:36:27</data_of_arrival>
  </train>
  <train>
   <train_number>774</train_number>
   <depart_st>Watkins</depart_st>
   <arriv_st>Palmyra</arriv_st>
   <data_of_departure>8/6/2002 17:46:4</data_of_departure>
   <data_of_arrival>17/4/2007 16:4:31</data_of_arrival>
  </train>
 </trains>
